common_metrics/__init__.py
common_metrics/metrics.py
common_metrics-0.0.6.dist-info/LICENSE
common_metrics-0.0.6.dist-info/METADATA
common_metrics-0.0.6.dist-info/WHEEL
common_metrics-0.0.6.dist-info/top_level.txt
common_metrics-0.0.6.dist-info/RECORD
