Metadata-Version: 2.1
Name: common_metrics
Version: 0.0.6
Summary: Package for commonly used metrics in bio-metrics.
Author-email: Sushrut Patwardhan <sushrutpatwardhan@gmail.com>
Project-URL: Homepage, https://github.com/Blazkowiz47/biometrics
Project-URL: Issues, https://github.com/Blazkowiz47/biometrics/issues
Classifier: Programming Language :: Python :: 3
Classifier: License :: OSI Approved :: MIT License
Classifier: Operating System :: OS Independent
Requires-Python: >=3.6
License-File: LICENSE
Requires-Dist: numpy
